LICENSE
README.md
setup.cfg
setup.py
pymean/__init__.py
pymean/enrichment.py
pymean.egg-info/PKG-INFO
pymean.egg-info/SOURCES.txt
pymean.egg-info/dependency_links.txt
pymean.egg-info/requires.txt
pymean.egg-info/top_level.txt
pymean/utils/__init__.py
pymean/utils/get_smpdb.py
pymean/utils/kegg_prep.py