Metadata-Version: 2.1
Name: pymean
Version: 0.22
Summary: The pyMEAN package is designed to facilitate semi-automated enrichment analysis for metabolomic experiments.
Home-page: https://github.com/AberystwythSystemsBiology/pyMEAN
Author: Keiron O'Shea
License: UNKNOWN
Keywords: metabolomics,enrichment analysis,omics
Platform: UNKNOWN
Classifier: Development Status :: 4 - Beta
Classifier: Intended Audience :: Science/Research
Classifier: Programming Language :: Python :: 3.6
Classifier: Programming Language :: Python :: 3.7
Classifier: Topic :: Scientific/Engineering
Requires-Python: >= 3.6
